masktools
masktools/superskims
