Metadata-Version: 1.1
Name: masktools
Version: 0.0.5
Summary: Tools for making DEIMOS slit masks
Home-page: https://github.com/adwasser/masktools
Author: Asher Wasserman
Author-email: adwasser@ucsc.edu
License: MIT
Download-URL: https://github.com/adwasser/masktools/tarball/0.0.5
Platform: UNKNOWN
